kgops/__init__.py
kgops/cli/__init__.py
kgops/cli/commands.py
kgops/cli/main.py
kgops/connectors/__init__.py
kgops/connectors/base.py
kgops/connectors/json_ld.py
kgops/connectors/neo4j.py
kgops/connectors/rdf.py
kgops/connectors/sparql.py
kgops/core/__init__.py
kgops/core/context.py
kgops/core/dataset.py
kgops/core/exceptions.py
kgops/core/forge.py
kgops/core/resource.py
kgops/mappings/__init__.py
kgops/mappings/base.py
kgops/mappings/ontology.py
kgops/mappings/schema.py
kgops/storage/__init__.py
kgops/storage/base.py
kgops/storage/database.py
kgops/storage/file.py
kgops/storage/memory.py
kgops/transforms/__init__.py
kgops/transforms/base.py
kgops/transforms/converter.py
kgops/transforms/mapper.py
kgops/transforms/validator.py
kgops/utils/__init__.py
kgops/utils/data_ingestion.py
kgops/utils/helpers.py
kgops/utils/logging.py
kgops/utils/serialization.py
kgops/utils/validation.py
kgops-0.1.2.dist-info/licenses/LICENSE
kgops-0.1.2.dist-info/METADATA
kgops-0.1.2.dist-info/WHEEL
kgops-0.1.2.dist-info/entry_points.txt
kgops-0.1.2.dist-info/top_level.txt
kgops-0.1.2.dist-info/RECORD
