Metadata-Version: 2.4
Name: kgops
Version: 0.1.2
Summary: KGOps - End-to-End Knowledge Graph Operations for RAG & Data Integration
Home-page: https://github.com/SohamChaudhari2004/kgops
Author: KGOps Team
Author-email: Soham Chaudhari <sohamchaudhari2004@gmail.com>
License: MIT
Project-URL: Homepage, https://github.com/SohamChaudhari2004/kgops
Project-URL: Documentation, https://github.com/SohamChaudhari2004/kgops
Project-URL: Repository, https://github.com/SohamChaudhari2004/kgops
Project-URL: Issues, https://github.com/SohamChaudhari2004/kgops/issues
Keywords: knowledge-graph,rag,nlp,ai,machine-learning
Classifier: Development Status :: 3 - Alpha
Classifier: Intended Audience :: Developers
Classifier: License :: OSI Approved :: MIT License
Classifier: Programming Language :: Python :: 3
Classifier: Programming Language :: Python :: 3.10
Classifier: Programming Language :: Python :: 3.11
Classifier: Programming Language :: Python :: 3.12
Requires-Python: >=3.10
License-File: LICENSE
Requires-Dist: networkx>=3.0
Requires-Dist: pandas>=2.0.0
Requires-Dist: numpy>=1.24.0
Requires-Dist: pydantic>=2.0.0
Requires-Dist: click>=8.0.0
Requires-Dist: rich>=13.0.0
Requires-Dist: pyyaml>=6.0
Requires-Dist: jsonschema>=4.0.0
Requires-Dist: python-dotenv>=1.0.0
Requires-Dist: typing-extensions>=4.5.0
Provides-Extra: dev
Requires-Dist: pytest>=7.0.0; extra == "dev"
Requires-Dist: pytest-cov>=4.0.0; extra == "dev"
Requires-Dist: black>=23.0.0; extra == "dev"
Requires-Dist: isort>=5.12.0; extra == "dev"
Requires-Dist: flake8>=6.0.0; extra == "dev"
Requires-Dist: mypy>=1.0.0; extra == "dev"
Requires-Dist: pre-commit>=3.0.0; extra == "dev"
Provides-Extra: docs
Requires-Dist: sphinx>=6.0.0; extra == "docs"
Requires-Dist: sphinx-rtd-theme>=1.2.0; extra == "docs"
Requires-Dist: sphinxcontrib-napoleon>=0.7; extra == "docs"
Provides-Extra: test
Requires-Dist: pytest>=7.0.0; extra == "test"
Requires-Dist: pytest-cov>=4.0.0; extra == "test"
Requires-Dist: pytest-mock>=3.10.0; extra == "test"
Dynamic: author
Dynamic: home-page
Dynamic: license-file
Dynamic: requires-python
